{
	"id": "008",
	"name": "Quận Hoàng Mai",
	"data": [
		{
			"id": "00316",
			"name": "Phường Đại Kim"
		},
		{
			"id": "00307",
			"name": "Phường Định Công"
		},
		{
			"id": "00325",
			"name": "Phường Giáp Bát"
		},
		{
			"id": "00337",
			"name": "Phường Hoàng Liệt"
		},
		{
			"id": "00322",
			"name": "Phường Hoàng Văn Thụ"
		},
		{
			"id": "00328",
			"name": "Phường Lĩnh Nam"
		},
		{
			"id": "00310",
			"name": "Phường Mai Động"
		},
		{
			"id": "00319",
			"name": "Phường Tân Mai"
		},
		{
			"id": "00301",
			"name": "Phường Thanh Trì"
		},
		{
			"id": "00331",
			"name": "Phường Thịnh Liệt"
		},
		{
			"id": "00334",
			"name": "Phường Trần Phú"
		},
		{
			"id": "00313",
			"name": "Phường Tương Mai"
		},
		{
			"id": "00304",
			"name": "Phường Vĩnh Hưng"
		},
		{
			"id": "00340",
			"name": "Phường Yên Sở"
		}
	]
}