{
	"id": 116,
	"name": "HUYỆN ĐẮK MIL",
	"fullname": "HUYỆN ĐẮK MIL, Đăk Nông",
	"data": [
		{
			"id": 1653,
			"name": "THỊ TRẤN ĐĂK MIL"
		},
		{
			"id": 1654,
			"name": "XÃ ĐẮK LAO"
		},
		{
			"id": 1655,
			"name": "XÃ ĐẮK RLA"
		},
		{
			"id": 1656,
			"name": "XÃ ĐẮK GẰN"
		},
		{
			"id": 1657,
			"name": "XÃ ĐỨC MẠNH"
		},
		{
			"id": 1658,
			"name": "XÃ ĐĂK NDRÓT"
		},
		{
			"id": 1659,
			"name": "XÃ ĐẮK SẮK"
		},
		{
			"id": 1660,
			"name": "XÃ THUẬN AN"
		},
		{
			"id": 1661,
			"name": "XÃ LONG SƠN"
		},
		{
			"id": 1662,
			"name": "XÃ ĐỨC MINH"
		}
	]
}