{
	"id": 48,
	"name": "QUẬN 4",
	"data": [
		{
			"id": 840,
			"name": "PHƯỜNG 9"
		},
		{
			"id": 841,
			"name": "PHƯỜNG 8"
		},
		{
			"id": 842,
			"name": "PHƯỜNG 10"
		},
		{
			"id": 843,
			"name": "PHƯỜNG 1"
		},
		{
			"id": 844,
			"name": "PHƯỜNG 12"
		},
		{
			"id": 845,
			"name": "PHƯỜNG 2"
		},
		{
			"id": 846,
			"name": "PHƯỜNG 3"
		},
		{
			"id": 847,
			"name": "PHƯỜNG 4"
		},
		{
			"id": 848,
			"name": "PHƯỜNG 5"
		},
		{
			"id": 849,
			"name": "PHƯỜNG 6"
		},
		{
			"id": 850,
			"name": "PHƯỜNG 18"
		},
		{
			"id": 851,
			"name": "PHƯỜNG 14"
		},
		{
			"id": 852,
			"name": "PHƯỜNG 15"
		},
		{
			"id": 853,
			"name": "PHƯỜNG 13"
		},
		{
			"id": 854,
			"name": "PHƯỜNG 16"
		}
	]
}