{
	"id": 682,
	"name": "HUYỆN LONG PHÚ",
	"fullname": "HUYỆN LONG PHÚ, Sóc Trăng",
	"data": [
		{
			"id": 11353,
			"name": "TT THỊ TRẤN LONG PHÚ"
		},
		{
			"id": 11354,
			"name": "XÃ TÂN THẠNH"
		},
		{
			"id": 11355,
			"name": "XÃ LONG PHÚ"
		},
		{
			"id": 11356,
			"name": "XÃ CHÂU KHÁNH"
		},
		{
			"id": 11357,
			"name": "XÃ VIÊN AN"
		},
		{
			"id": 11358,
			"name": "XÃ LIÊU TÚ"
		},
		{
			"id": 11359,
			"name": "XÃ ĐẠI ÂN II"
		},
		{
			"id": 11360,
			"name": "XÃ TRƯỜNG KHÁNH"
		},
		{
			"id": 11361,
			"name": "XÃ HẬU THẠNH"
		},
		{
			"id": 11362,
			"name": "XÃ LONG ĐỨC"
		},
		{
			"id": 11363,
			"name": "XÃ TÂN HƯNG"
		},
		{
			"id": 11364,
			"name": "XÃ PHÚ HỮU"
		},
		{
			"id": 11365,
			"name": "XÃ ĐẠI NGÃI"
		},
		{
			"id": 11366,
			"name": "XÃ TRUNG BÌNH"
		},
		{
			"id": 11367,
			"name": "XÃ SONG PHỤNG"
		}
	]
}