{
	"id": "774",
	"name": "Quận 5",
	"data": [
		{
			"id": "27325",
			"name": "Phường 01"
		},
		{
			"id": "27313",
			"name": "Phường 02"
		},
		{
			"id": "27307",
			"name": "Phường 03"
		},
		{
			"id": "27301",
			"name": "Phường 04"
		},
		{
			"id": "27334",
			"name": "Phường 05"
		},
		{
			"id": "27337",
			"name": "Phường 06"
		},
		{
			"id": "27322",
			"name": "Phường 07"
		},
		{
			"id": "27316",
			"name": "Phường 08"
		},
		{
			"id": "27304",
			"name": "Phường 09"
		},
		{
			"id": "27340",
			"name": "Phường 10"
		},
		{
			"id": "27328",
			"name": "Phường 11"
		},
		{
			"id": "27310",
			"name": "Phường 12"
		},
		{
			"id": "27343",
			"name": "Phường 13"
		},
		{
			"id": "27331",
			"name": "Phường 14"
		}
	]
}