{
	"id": "846",
	"name": "Huyện Tiểu Cần",
	"data": [
		{
			"id": "29344",
			"name": "Thị trấn Cầu Quan"
		},
		{
			"id": "29353",
			"name": "Xã Hiếu Trung"
		},
		{
			"id": "29350",
			"name": "Xã Hiếu Tử"
		},
		{
			"id": "29359",
			"name": "Xã Hùng Hòa"
		},
		{
			"id": "29356",
			"name": "Xã Long Thới"
		},
		{
			"id": "29368",
			"name": "Xã Ngãi Hùng"
		},
		{
			"id": "29347",
			"name": "Xã Phú Cần"
		},
		{
			"id": "29371",
			"name": "Xã Tân Hòa"
		},
		{
			"id": "29362",
			"name": "Xã Tân Hùng"
		},
		{
			"id": "29365",
			"name": "Xã Tập Ngãi"
		},
		{
			"id": "29341",
			"name": "Thị trấn Tiểu Cần"
		}
	]
}