{
	"id": 94,
	"name": "HUYỆN GÒ CÔNG TÂY",
	"fullname": "HUYỆN GÒ CÔNG TÂY, Tiền Giang",
	"data": [
		{
			"id": 1367,
			"name": "THỊ TRẤN VĨNH BÌNH"
		},
		{
			"id": 1368,
			"name": "XÃ ĐỒNG SƠN"
		},
		{
			"id": 1369,
			"name": "XÃ LONG BÌNH"
		},
		{
			"id": 1370,
			"name": "XÃ THẠNH NHỰT"
		},
		{
			"id": 1371,
			"name": "XÃ BÌNH PHÚ"
		},
		{
			"id": 1372,
			"name": "XÃ BÌNH TÂN"
		},
		{
			"id": 1373,
			"name": "XÃ ĐỒNG THẠNH"
		},
		{
			"id": 1374,
			"name": "XÃ LONG VĨNH"
		},
		{
			"id": 1375,
			"name": "XÃ THÀNH CÔNG"
		},
		{
			"id": 1376,
			"name": "XÃ THẠNH TRỊ"
		},
		{
			"id": 1377,
			"name": "XÃ VĨNH HỰU"
		},
		{
			"id": 1378,
			"name": "XÃ YÊN LUÔNG"
		},
		{
			"id": 1379,
			"name": "XÃ BÌNH NHÌ"
		}
	]
}